{
"_comment1":"Verbal morphology",
"Sing":"SG",
"Plur":"PL",
"Def":"DEF",
"Ind":"IND",
"Pres":"PRS",
"Past":"PAST",
"Impf":"IMPF",
"Fin":"FIN",
"Rel":"REL",
"Part":"PASTP",
"_comment2":"Nominal morphology",
"Nom":"NOM",
"Acc":"ACC",
"Dat":"DAT",
"Gen":"GEN",
"Art":"ART",
"Nom,Acc":"NOM/ACC",
"Nom,Dat":"NOM/DAT",
"Nom,Gen":"NOM/GEN",
"Acc,Dat":"ACC/DAT",
"Acc,Gen":"ACC/GEN",
"Dat,Gen":"DAT/GEN",
"Nom,Acc,Dat":"NOM/ACC/DAT",
"Masc":"M",
"Neut":"N",
"Masc,Neut":"M/N",
"Fem":"F",
"Int":"INT",
"Dem":"DEM"
}